{
	"title": "月经期间吃什么好？",
	"update": "2016-03-18 18:00",
	"content": [{"type": "article", "content": "在生理期，女性的抵抗能力降低，情绪上易波动，稍有不注意还很有可能引起经期不适等症状。那么女性在月经期间吃什么能够避免或减轻经期不适呢？"},
				{"type": "title", "content": "首先，多食用一些温补类食物"},
				{"type": "article", "content": "女性的体质偏寒性，因此应该多食用一些温补类食物，如羊肉、鸡肉、牛奶、红糖、当归、益母草、桂圆等，可以起到活血化瘀的作用。如果女性经期出现食欲差、腰痛等症状，那么建议食用营养丰富、健脾开胃以及易消化的食品，如大枣、面条、薏苡仁粥等。"},
				{"type": "title", "content": "其次，吃些性温的水果"},
				{"type": "article", "content": "很多水果女性在经期食用也是非常好的，能够预防发生便秘，以及避免盆腔充血等症状。女性可以挑一些性温或性热的水果，如：苹果、葡萄、无花果、榴莲，荔枝、人参果、樱桃、桂圆、桃子、石榴等水果。"},
	            {"type": "img", "content": "images/trouble/i30a.png"},
				{"type": "title", "content": "最后，吃富含维生素B、维生素E的食物"},
				{"type": "article", "content": "女性在来经期间，由于激素分泌影响和身体不适等原因，女性时常会出现一些不良的情绪变化，而维生素B6有助于人体合成提升情绪的神经传递素，从而保持情绪上的稳定，像胡萝卜、菜花等食物都能够为人体提供丰富的维生素B6。还有些女性在月经期间会出现胸部不适、乳房胀痛等经期不适的情况，通常情况前列腺素过多是引发一系列经前疼痛的原因。而在众多蔬菜中，菠菜中富含维生素E，能减低前列腺素的产生，有助于缓解疼痛。"},
	            {"type": "img", "content": "images/trouble/i30b.png"}]
}